daftlistings/__init__.py
daftlistings/daft.py
daftlistings/enums.py
daftlistings/listing.py
daftlistings/location.py
daftlistings/map_visualization.py
daftlistings-2.0.5.dist-info/licenses/LICENSE
daftlistings-2.0.5.dist-info/METADATA
daftlistings-2.0.5.dist-info/WHEEL
daftlistings-2.0.5.dist-info/top_level.txt
daftlistings-2.0.5.dist-info/RECORD
