Metadata-Version: 2.4
Name: daftlistings
Version: 2.0.5
Summary: A library that enables programmatic interaction with daft.ie. Daft.ie has nationwide coverage and contains about 80% of the total available properties in Ireland.
Home-page: https://github.com/AnthonyBloomer/daftlistings
Author: Anthony Bloomer
Author-email: ant0@protonmail.ch
License: MIT
Keywords: daft,real estate,daft.ie
Classifier: Intended Audience :: Developers
Classifier: License :: OSI Approved :: MIT License
Classifier: Topic :: Software Development :: Libraries
Classifier: Programming Language :: Python
Classifier: Programming Language :: Python :: 3.9
License-File: LICENSE
Requires-Dist: requests
Requires-Dist: folium
Dynamic: author
Dynamic: author-email
Dynamic: classifier
Dynamic: description
Dynamic: description-content-type
Dynamic: home-page
Dynamic: keywords
Dynamic: license
Dynamic: license-file
Dynamic: requires-dist
Dynamic: summary
